{"nm":"EIMAN","ddd":0,"h":3240,"w":5760,"meta":{"g":"@lottiefiles/toolkit-js 0.73.1","tc":"#8e8e8e"},"layers":[{"ty":4,"nm":"Shape Layer 5","sr":1,"st":29,"op":929,"ip":23,"ln":"50","hasMask":false,"ao":0,"ks":{"a":{"a":0,"k":[0,0]},"s":{"a":0,"k":[100,100]},"p":{"a":0,"k":[2624,1725]},"r":{"a":0,"k":0},"sa":{"a":0,"k":0},"o":{"a":1,"k":[{"o":{"x":0.167,"y":0.167},"i":{"x":0.833,"y":0.833},"s":[0],"t":29},{"s":[100],"t":32}]}},"shapes":[{"ty":"gr","nm":"Shape 1","it":[{"ty":"sh","nm":"Path 1","d":1,"ks":{"a":0,"k":{"c":false,"i":[[0,0],[0,0]],"o":[[0,0],[0,0]],"v":[[-35.089,-8.576],[206.282,-107.416]]}}},{"ty":"st","nm":"Stroke 1","lc":2,"lj":1,"ml":4,"o":{"a":0,"k":100},"w":{"a":0,"k":149},"c":{"a":0,"k":[1,1,1]}},{"ty":"tr","a":{"a":0,"k":[0,0]},"s":{"a":0,"k":[100,100]},"p":{"a":0,"k":[6,2]},"r":{"a":0,"k":0},"sa":{"a":0,"k":0},"o":{"a":0,"k":100}}]},{"ty":"tm","nm":"Trim Paths 1","e":{"a":0,"k":100},"o":{"a":0,"k":0},"s":{"a":1,"k":[{"o":{"x":0.333,"y":0},"i":{"x":0.667,"y":1},"s":[100],"t":29},{"s":[0],"t":45}]},"m":1}],"ind":1},{"ty":4,"nm":"Shape Layer 4","sr":1,"st":29,"op":929,"ip":23,"ln":"48","hasMask":false,"ao":0,"ks":{"a":{"a":0,"k":[0,0]},"s":{"a":0,"k":[100,100]},"p":{"a":0,"k":[2880,1620]},"r":{"a":0,"k":0},"sa":{"a":0,"k":0},"o":{"a":1,"k":[{"o":{"x":0.167,"y":0.167},"i":{"x":0.833,"y":0.833},"s":[0],"t":29},{"s":[100],"t":32}]}},"shapes":[{"ty":"gr","nm":"Shape 1","it":[{"ty":"sh","nm":"Path 1","d":1,"ks":{"a":0,"k":{"c":false,"i":[[0,0],[0,0]],"o":[[0,0],[0,0]],"v":[[-35.089,-8.576],[206.282,-107.416]]}}},{"ty":"st","nm":"Stroke 1","lc":2,"lj":1,"ml":4,"o":{"a":0,"k":100},"w":{"a":0,"k":149},"c":{"a":0,"k":[1,1,1]}},{"ty":"tr","a":{"a":0,"k":[0,0]},"s":{"a":0,"k":[100,100]},"p":{"a":0,"k":[6,2]},"r":{"a":0,"k":0},"sa":{"a":0,"k":0},"o":{"a":0,"k":100}}]},{"ty":"tm","nm":"Trim Paths 1","e":{"a":1,"k":[{"o":{"x":0.333,"y":0},"i":{"x":0.667,"y":1},"s":[0],"t":29},{"s":[100],"t":45}]},"o":{"a":0,"k":0},"s":{"a":0,"k":0},"m":1}],"ind":2},{"ty":3,"nm":"HAND 1","sr":1,"st":0,"op":900,"ip":0,"ln":"46","hasMask":false,"ao":0,"ks":{"a":{"a":0,"k":[50,50]},"s":{"a":1,"k":[{"s":[40,40,102.564],"i":{"x":[0.077,0.077,0.667],"y":[1,1,1]},"o":{"x":[0.333,0.333,0.333],"y":[0,0,0]},"t":0},{"s":[100,100,100],"i":{"x":[0.667,0.667,0.667],"y":[1,1,1]},"o":{"x":[0.333,0.333,0.333],"y":[0,0,0]},"t":45}]},"p":{"a":1,"k":[{"o":{"x":0.333,"y":0},"i":{"x":0.077,"y":1},"s":[1200,1620.018],"t":0},{"s":[2656.494,1620.018],"t":45}]},"r":{"a":1,"k":[{"o":{"x":0.333,"y":0},"i":{"x":0.077,"y":1},"s":[-100],"t":0},{"s":[0],"t":45}]},"sa":{"a":0,"k":0},"o":{"a":0,"k":100}},"ind":3},{"ty":3,"nm":"HAND 2","sr":1,"st":0,"op":900,"ip":0,"ln":"40","hasMask":false,"ao":0,"ks":{"a":{"a":0,"k":[50,50]},"s":{"a":1,"k":[{"s":[40,40,102.564],"i":{"x":[0.077,0.077,0.667],"y":[1,1,1]},"o":{"x":[0.333,0.333,0.333],"y":[0,0,0]},"t":0},{"s":[100,100,100],"i":{"x":[0.667,0.667,0.667],"y":[1,1,1]},"o":{"x":[0.333,0.333,0.333],"y":[0,0,0]},"t":45}]},"p":{"a":1,"k":[{"o":{"x":0.333,"y":0},"i":{"x":0.077,"y":1},"s":[4535.423,1619.921],"t":0},{"s":[3012.423,1619.921],"t":45}]},"r":{"a":1,"k":[{"o":{"x":0.333,"y":0},"i":{"x":0.077,"y":1},"s":[100],"t":0},{"s":[0],"t":45}]},"sa":{"a":0,"k":0},"o":{"a":0,"k":100}},"ind":4},{"ty":4,"nm":"Shape Layer 2","sr":1,"st":0,"op":900,"ip":0,"ln":"44","tt":1,"hasMask":false,"ao":0,"ks":{"a":{"a":0,"k":[0,0]},"s":{"a":0,"k":[100,100]},"p":{"a":0,"k":[181.762,49.885]},"r":{"a":0,"k":-180},"sa":{"a":0,"k":0},"o":{"a":0,"k":100}},"shapes":[{"ty":"gr","nm":"Shape 1","it":[{"ty":"sh","nm":"Path 1","d":1,"ks":{"a":0,"k":{"c":false,"i":[[0,0],[0,0],[-131.651,-260.863],[189.896,-124.932],[151.154,141.402]],"o":[[0,0],[0,0],[106.818,211.659],[-185.286,121.898],[-151.155,-141.403]],"v":[[-420.082,-86.513],[284.494,-386.384],[733.081,-210.85],[606.306,337.695],[121.149,279.184]]}}},{"ty":"st","nm":"Stroke 1","lc":2,"lj":1,"ml":4,"o":{"a":0,"k":100},"w":{"a":0,"k":191},"c":{"a":0,"k":[1,1,1]}},{"ty":"tr","a":{"a":0,"k":[0,0]},"s":{"a":0,"k":[100,100]},"p":{"a":0,"k":[0,0]},"r":{"a":0,"k":0},"sa":{"a":0,"k":0},"o":{"a":0,"k":100}}]},{"ty":"tm","nm":"Trim Paths 1","e":{"a":1,"k":[{"o":{"x":0.333,"y":0},"i":{"x":0.207,"y":1},"s":[0],"t":14},{"s":[100],"t":45}]},"o":{"a":0,"k":0},"s":{"a":0,"k":0},"m":1}],"ind":5,"parent":3,"tp":6},{"ty":4,"nm":"HAND 1","sr":1,"st":0,"op":900,"ip":0,"ln":"26","hasMask":false,"td":1,"ao":0,"ks":{"a":{"a":0,"k":[0,0]},"s":{"a":0,"k":[64,64]},"p":{"a":0,"k":[-20.262,50]},"r":{"a":0,"k":0},"sa":{"a":0,"k":0},"o":{"a":0,"k":100}},"shapes":[{"ty":"gr","nm":"Group 1","it":[{"ty":"sh","nm":"Path 1","d":1,"ks":{"a":0,"k":{"c":true,"i":[[59.347,-24.288],[0,0],[93.774,0],[135.168,208.449],[0,151.216],[-0.423,11.616],[-216.263,123.55],[-225.137,-119.535],[0,0],[17.706,-7.213],[0,0],[16.187,7.222],[142.362,-80.977],[7.6,-168.534],[0,-8.447],[-57.655,-88.49],[-223.023,90.814],[0,0],[-24.285,-59.346]],"o":[[0,0],[-91.449,37.381],[-240.549,0],[-81.941,-126.295],[0,-11.827],[11.194,-246.253],[222.178,-126.928],[0,0],[16.882,8.974],[0,0],[-16.415,6.688],[-147.154,-65.651],[-148.893,85.112],[-0.423,8.236],[0,106.232],[127.352,196.623],[0,0],[59.558,-24.288],[24.079,59.347]],"v":[[968.911,275.143],[-28.563,681.904],[-309.03,737.237],[-915.793,411.152],[-1041.242,-13.139],[-1040.396,-48.62],[-677.142,-638.91],[37.332,-650.526],[158.898,-585.91],[156.822,-545.129],[-52.681,-459.783],[-103.666,-460.833],[-562.042,-437.219],[-808.293,-38.271],[-808.927,-13.139],[-720.861,284.646],[-116.207,466.907],[881.267,60.146],[1032.692,123.715]]}}},{"ty":"fl","nm":"Fill 1","c":{"a":0,"k":[0.1373,0.1216,0.1255]},"r":1,"o":{"a":0,"k":100}},{"ty":"tr","a":{"a":0,"k":[0,0]},"s":{"a":0,"k":[100,100]},"p":{"a":0,"k":[0,0]},"r":{"a":0,"k":0},"sa":{"a":0,"k":0},"o":{"a":0,"k":100}}]}],"ind":6,"parent":3},{"ty":4,"nm":"Shape Layer 1","sr":1,"st":0,"op":900,"ip":0,"ln":"32","tt":1,"hasMask":false,"ao":0,"ks":{"a":{"a":0,"k":[0,0]},"s":{"a":0,"k":[100,100]},"p":{"a":0,"k":[-82.423,50.079]},"r":{"a":0,"k":0},"sa":{"a":0,"k":0},"o":{"a":0,"k":100}},"shapes":[{"ty":"gr","nm":"Shape 1","it":[{"ty":"sh","nm":"Path 1","d":1,"ks":{"a":0,"k":{"c":false,"i":[[0,0],[0,0],[-131.651,-260.863],[189.896,-124.932],[151.154,141.402]],"o":[[0,0],[0,0],[106.818,211.659],[-185.286,121.898],[-151.155,-141.403]],"v":[[-420.082,-86.513],[284.494,-386.384],[733.081,-210.85],[606.306,337.695],[121.149,279.184]]}}},{"ty":"st","nm":"Stroke 1","lc":2,"lj":1,"ml":4,"o":{"a":0,"k":100},"w":{"a":0,"k":191},"c":{"a":0,"k":[1,1,1]}},{"ty":"tr","a":{"a":0,"k":[0,0]},"s":{"a":0,"k":[100,100]},"p":{"a":0,"k":[0,0]},"r":{"a":0,"k":0},"sa":{"a":0,"k":0},"o":{"a":0,"k":100}}]},{"ty":"tm","nm":"Trim Paths 1","e":{"a":1,"k":[{"o":{"x":0.333,"y":0},"i":{"x":0.207,"y":1},"s":[0],"t":14},{"s":[100],"t":45}]},"o":{"a":0,"k":0},"s":{"a":0,"k":0},"m":1}],"ind":7,"parent":4,"tp":8},{"ty":4,"nm":"HAND 2","sr":1,"st":0,"op":900,"ip":0,"ln":"25","hasMask":false,"td":1,"ao":0,"ks":{"a":{"a":0,"k":[0,0]},"s":{"a":0,"k":[64,64]},"p":{"a":0,"k":[120.924,50]},"r":{"a":0,"k":0},"sa":{"a":0,"k":0},"o":{"a":0,"k":100}},"shapes":[{"ty":"gr","nm":"Group 1","it":[{"ty":"sh","nm":"Path 1","d":1,"ks":{"a":0,"k":{"c":true,"i":[[0,-151.215],[0.417,-11.827],[216.258,-123.337],[126.717,0],[108.974,57.867],[0,0],[-17.696,7.215],[0,0],[-16.189,-7.219],[-142.365,81.381],[-7.606,168.535],[0,8.448],[57.656,88.703],[222.807,-91.025],[0,0],[19.378,67.702],[-55.21,22.514],[0,0],[-187.961,-289.76]],"o":[[0,12.038],[-11.194,246.043],[-114.683,65.471],[-118.689,0],[0,0],[-16.87,-8.979],[0,0],[16.414,-6.692],[147.339,65.704],[148.894,-85.111],[0.422,-8.236],[0,-106.231],[-127.351,-196.411],[0,0],[-63.374,25.935],[-16.407,-57.322],[0,0],[326.089,-132.841],[81.947,126.505]],"v":[[1041.176,12.988],[1040.542,48.68],[677.288,638.759],[309.171,737.176],[-37.398,650.376],[-158.809,585.759],[-156.728,544.986],[52.621,459.637],[103.607,460.674],[562.182,437.068],[808.439,38.12],[808.861,12.988],[721.001,-284.797],[116.352,-466.846],[-881.121,-60.085],[-1036.878,-136.364],[-966.019,-276.415],[28.703,-682.054],[915.933,-411.302]]}}},{"ty":"fl","nm":"Fill 1","c":{"a":0,"k":[0.1373,0.1216,0.1255]},"r":1,"o":{"a":0,"k":100}},{"ty":"tr","a":{"a":0,"k":[0,0]},"s":{"a":0,"k":[100,100]},"p":{"a":0,"k":[0,0]},"r":{"a":0,"k":0},"sa":{"a":0,"k":0},"o":{"a":0,"k":100}}]}],"ind":8,"parent":4}],"v":"5.7.0","fr":30,"op":121,"ip":0,"assets":[]}